wutils/__init__.py
wutils/df.py
wutils/general.py
wutils/mat.py
wutils/tensor.py
wutils/torch.py
wutils-0.2.3.dist-info/LICENSE
wutils-0.2.3.dist-info/METADATA
wutils-0.2.3.dist-info/WHEEL
wutils-0.2.3.dist-info/top_level.txt
wutils-0.2.3.dist-info/RECORD
