Metadata-Version: 2.1
Name: wutils
Version: 0.2.3
Summary: A collection of useful functions/classes for data analysis and ML.
Home-page: http://pypi.python.org/pypi/wutils/
Author: William Shiao
Author-email: willshiao@gmail.com
License: LICENSE
Platform: UNKNOWN
License-File: LICENSE
Requires-Dist: scikit-learn
Requires-Dist: numpy
Requires-Dist: seaborn
Requires-Dist: pytest
Requires-Dist: xgboost
Requires-Dist: scipy
Requires-Dist: matplotlib
